alignak_webui/__init__.py
alignak_webui/app.py
alignak_webui/webui.py
alignak_webui/backend/__init__.py
alignak_webui/backend/alignak_ws_client.py
alignak_webui/backend/backend.py
alignak_webui/backend/datamanager.py
alignak_webui/backend/glpi_ws_client.py
alignak_webui/locales/fr_FR.mo
alignak_webui/locales/fr_FR.po
alignak_webui/locales/messages.pot
alignak_webui/objects/__init__.py
alignak_webui/objects/element.py
alignak_webui/objects/element_state.py
alignak_webui/objects/item_actions.py
alignak_webui/objects/item_alignak.py
alignak_webui/objects/item_backend_grafana.py
alignak_webui/objects/item_backend_graphite.py
alignak_webui/objects/item_backend_influxdb.py
alignak_webui/objects/item_backend_statsd.py
alignak_webui/objects/item_command.py
alignak_webui/objects/item_daemon.py
alignak_webui/objects/item_history.py
alignak_webui/objects/item_host.py
alignak_webui/objects/item_hostdependency.py
alignak_webui/objects/item_hostescalation.py
alignak_webui/objects/item_hostgroup.py
alignak_webui/objects/item_livesynthesis.py
alignak_webui/objects/item_log.py
alignak_webui/objects/item_realm.py
alignak_webui/objects/item_service.py
alignak_webui/objects/item_servicedependency.py
alignak_webui/objects/item_serviceescalation.py
alignak_webui/objects/item_servicegroup.py
alignak_webui/objects/item_timeperiod.py
alignak_webui/objects/item_user.py
alignak_webui/objects/item_usergroup.py
alignak_webui/objects/item_userrestrictrole.py
alignak_webui/plugins/__init__.py
alignak_webui/plugins/actions/__init__.py
alignak_webui/plugins/actions/actions.py
alignak_webui/plugins/actions/external_commands.py
alignak_webui/plugins/actions/views/acknowledge_form_add.tpl
alignak_webui/plugins/actions/views/command_form_add.tpl
alignak_webui/plugins/actions/views/downtime_form_add.tpl
alignak_webui/plugins/actions/views/recheck_form_add.tpl
alignak_webui/plugins/alignak/__init__.py
alignak_webui/plugins/alignak/alignak.py
alignak_webui/plugins/alignak/settings.cfg
alignak_webui-0.12.2.dist-info/AUTHORS
alignak_webui-0.12.2.dist-info/LICENSE
alignak_webui-0.12.2.dist-info/METADATA
alignak_webui-0.12.2.dist-info/WHEEL
alignak_webui-0.12.2.dist-info/dependency_links.txt
alignak_webui-0.12.2.dist-info/entry_points.txt
alignak_webui-0.12.2.dist-info/top_level.txt
alignak_webui-0.12.2.dist-info/RECORD
